maptools/__init__.py
maptools/_accumulate.py
maptools/_cc.py
maptools/_crop.py
maptools/_dilate.py
maptools/_edit.py
maptools/_erode.py
maptools/_fft.py
maptools/_filter.py
maptools/_fit.py
maptools/_fsc.py
maptools/_fsc3d.py
maptools/_genmask.py
maptools/_map2mtz.py
maptools/_mask.py
maptools/_pdb2map.py
maptools/_rebin.py
maptools/_reorder.py
maptools/_rescale.py
maptools/_rotate.py
maptools/_segment.py
maptools/_threshold.py
maptools/_transform.py
maptools/_version.py
maptools/command_line.py
maptools/external.py
maptools/util.py
maptools/engines/__init__.py
maptools-0.3.6.dist-info/LICENSE
maptools-0.3.6.dist-info/METADATA
maptools-0.3.6.dist-info/WHEEL
maptools-0.3.6.dist-info/entry_points.txt
maptools-0.3.6.dist-info/top_level.txt
maptools-0.3.6.dist-info/RECORD
