Metadata-Version: 2.1
Name: maptools
Version: 0.3.6
Summary: Manipulate maps
Home-page: https://github.com/rosalindfranklininstitute/maptools
Author: James Parkhurst
Author-email: james.parkhurst@diamond.ac.uk
License: Apache
Project-URL: Source, https://github.com/rosalindfranklininstitute/maptools
Project-URL: Tracker, https://github.com/rosalindfranklininstitute/maptools/issues
Keywords: EM
Platform: unix
Platform: linux
Platform: osx
Platform: cygwin
Platform: win32
Classifier: Development Status :: 4 - Beta
Classifier: Intended Audience :: Developers
Classifier: License :: OSI Approved :: BSD License
Classifier: Operating System :: POSIX
Classifier: Operating System :: Microsoft :: Windows
Classifier: Operating System :: MacOS :: MacOS X
Classifier: Topic :: Utilities
Classifier: Programming Language :: Python :: 3.4
Classifier: Programming Language :: Python :: 3.5
Classifier: Programming Language :: Python :: 3.6
Classifier: Programming Language :: Python :: 3.7
License-File: LICENSE
Requires-Dist: gemmi
Requires-Dist: matplotlib
Requires-Dist: mrcfile
Requires-Dist: numpy
Requires-Dist: pyyaml
Requires-Dist: scipy
Requires-Dist: scikit-image
Provides-Extra: build_sphinx
Requires-Dist: sphinx ; extra == 'build_sphinx'
Requires-Dist: sphinx-rtd-theme ; extra == 'build_sphinx'
Provides-Extra: test
Requires-Dist: pytest ; extra == 'test'
Requires-Dist: pytest-cov ; extra == 'test'
Requires-Dist: mock ; extra == 'test'
